airflow_kbo/__init__.py
airflow_kbo/__version__
airflow_kbo/kubernetes_base_operator.py
airflow_kbo/kubernetes_util.py
airflow_kube_base_operator-0.0.1.dist-info/LICENSE
airflow_kube_base_operator-0.0.1.dist-info/METADATA
airflow_kube_base_operator-0.0.1.dist-info/WHEEL
airflow_kube_base_operator-0.0.1.dist-info/top_level.txt
airflow_kube_base_operator-0.0.1.dist-info/RECORD
